israwave/__init__.py
israwave/config.json
israwave/helpers.py
israwave/logging.py
israwave/model.py
israwave/segment.py
israwave/symbols.py
israwave/tensors.py
israwave/tokenizer.py
israwave-0.1.8.dist-info/METADATA
israwave-0.1.8.dist-info/WHEEL
israwave-0.1.8.dist-info/RECORD
